{
  "total_downloads": 290453646,
  "total_last_month": 15086317,
  "timestamp": "2026-06-25T03:20:36.983927Z",
  "packages": [
    {
      "package": "ultralytics",
      "last_day": 318406,
      "last_week": 2107106,
      "last_month": 8678202,
      "total": 198751710
    },
    {
      "package": "ultralytics-actions",
      "last_day": 98,
      "last_week": 767,
      "last_month": 4491,
      "total": 259090
    },
    {
      "package": "ultralytics-thop",
      "last_day": 234948,
      "last_week": 1559593,
      "last_month": 6365857,
      "total": 89915921
    },
    {
      "package": "hub-sdk",
      "last_day": 1224,
      "last_week": 6669,
      "last_month": 26693,
      "total": 1224756
    },
    {
      "package": "mkdocs-ultralytics-plugin",
      "last_day": 307,
      "last_week": 2531,
      "last_month": 10942,
      "total": 296715
    },
    {
      "package": "ultralytics-autoimport",
      "last_day": 15,
      "last_week": 48,
      "last_month": 132,
      "total": 5454
    }
  ]
}
